dask4dvc/__init__.py
dask4dvc/cli/__init__.py
dask4dvc/cli/main.py
dask4dvc/dvc_repro.py
dask4dvc/utils/__init__.py
dask4dvc/utils/dask.py
dask4dvc-0.2.3.dist-info/LICENSE
dask4dvc-0.2.3.dist-info/METADATA
dask4dvc-0.2.3.dist-info/WHEEL
dask4dvc-0.2.3.dist-info/entry_points.txt
dask4dvc-0.2.3.dist-info/RECORD
