Metadata-Version: 2.1
Name: dask4dvc
Version: 0.2.3
Summary: Use dask to run the DVC graph
License: Apache-2.0
Keywords: data-science,HPC,dask,DVC
Author: zincwarecode
Author-email: zincwarecode@gmail.com
Requires-Python: >=3.8,<4.0
Classifier: License :: OSI Approved :: Apache Software License
Classifier: Programming Language :: Python :: 3
Classifier: Programming Language :: Python :: 3.8
Classifier: Programming Language :: Python :: 3.9
Classifier: Programming Language :: Python :: 3.10
Classifier: Programming Language :: Python :: 3.11
Requires-Dist: bokeh (>=2.4.2,<3)
Requires-Dist: dask (>=2022.7.1,<2023.0.0)
Requires-Dist: dask-jobqueue (>=0.8.1,<0.9.0)
Requires-Dist: distributed (>=2022.7.1,<2023.0.0)
Requires-Dist: dvc (>=2.54.0,<3.0.0)
Requires-Dist: typer[all] (>=0.7.0,<0.8.0)
Project-URL: repository, https://github.com/zincware/dask4dvc
